example.py
sanic_token_auth/__init__.py
sanic_token_auth-0.2.0.dist-info/AUTHORS.rst
sanic_token_auth-0.2.0.dist-info/METADATA
sanic_token_auth-0.2.0.dist-info/WHEEL
sanic_token_auth-0.2.0.dist-info/top_level.txt
sanic_token_auth-0.2.0.dist-info/RECORD
