Metadata-Version: 2.1
Name: sanic-token-auth
Version: 0.2.0
Summary: A simple token-based auth plugin for Sanic
Home-page: https://github.com/saabeilin/sanic-token-auth
Author: Sergei Beilin
Author-email: saabeilin@gmail.com
License: MIT license
Keywords: sanic,authentication
Classifier: Development Status :: 3 - Alpha
Classifier: Intended Audience :: Developers
Classifier: License :: OSI Approved :: MIT License
Classifier: Operating System :: Unix
Classifier: Operating System :: POSIX
Classifier: Operating System :: Microsoft :: Windows
Classifier: Programming Language :: Python
Classifier: Programming Language :: Python :: 3.9
Classifier: Programming Language :: Python :: 3.10
Classifier: Programming Language :: Python :: 3.11
Classifier: Programming Language :: Python :: Implementation :: CPython
Classifier: Programming Language :: Python :: Implementation :: PyPy
Classifier: Topic :: Utilities
License-File: AUTHORS.rst
Requires-Dist: sanic
